tests/__init__.py
tests/test_data_array.py
vtke/__init__.py
vtke/data_array.py
vtke/format.py
vtke/utils.py
vtke-0.0.2.dist-info/DESCRIPTION.rst
vtke-0.0.2.dist-info/METADATA
vtke-0.0.2.dist-info/RECORD
vtke-0.0.2.dist-info/WHEEL
vtke-0.0.2.dist-info/metadata.json
vtke-0.0.2.dist-info/top_level.txt
